grasp/__init__.py
grasp/_async_client.py
grasp/_browser.py
grasp/_client.py
grasp/_container.py
grasp/_exceptions.py
grasp/_http.py
grasp/_models.py
grasp/_types.py
grasp/_version.py
grasp/py.typed
grasp_sdk-0.2.0.dist-info/METADATA
grasp_sdk-0.2.0.dist-info/WHEEL
grasp_sdk-0.2.0.dist-info/top_level.txt
grasp_sdk-0.2.0.dist-info/RECORD
