Metadata-Version: 2.4
Name: grasp-sdk
Version: 0.2.0
Summary: Official Python SDK for the Grasp browser automation platform
Author-email: Grasp Team <dev@getgrasp.ai>
License: MIT
Project-URL: Homepage, https://getgrasp.ai
Project-URL: Documentation, https://docs.getgrasp.ai
Project-URL: Repository, https://github.com/getgrasp-ai/grasp
Project-URL: Issues, https://github.com/getgrasp-ai/grasp/issues
Keywords: browser,automation,chrome,devtools,cdp,playwright,puppeteer
Classifier: Development Status :: 3 - Alpha
Classifier: Programming Language :: Python :: 3
Classifier: Programming Language :: Python :: 3.8
Classifier: Programming Language :: Python :: 3.9
Classifier: Programming Language :: Python :: 3.10
Classifier: Programming Language :: Python :: 3.11
Classifier: Programming Language :: Python :: 3.12
Classifier: Intended Audience :: Developers
Classifier: License :: OSI Approved :: MIT License
Classifier: Topic :: Software Development :: Libraries :: Python Modules
Classifier: Topic :: Internet :: WWW/HTTP :: Browsers
Requires-Python: >=3.8
Requires-Dist: httpx>=0.24.0
Requires-Dist: pydantic>=2.0
Requires-Dist: pydantic-core>=2.0
Requires-Dist: python-dateutil>=2.8
Requires-Dist: typing-extensions>=4.0; python_version < "3.10"
Provides-Extra: dev
Requires-Dist: pytest>=7.0; extra == "dev"
Requires-Dist: pytest-asyncio>=0.20; extra == "dev"
Requires-Dist: pytest-httpx>=0.22; extra == "dev"
Requires-Dist: pytest-sugar>=0.9.7; extra == "dev"
Requires-Dist: pytest-watch>=4.2.0; extra == "dev"
Requires-Dist: pytest-xdist>=3.0; extra == "dev"
Requires-Dist: rich>=13.0; extra == "dev"
Requires-Dist: pytest-cov>=4.0; extra == "dev"
Requires-Dist: playwright>=1.40; extra == "dev"
Requires-Dist: black>=23.0; extra == "dev"
Requires-Dist: mypy>=1.0; extra == "dev"
Requires-Dist: ruff>=0.1.0; extra == "dev"
Requires-Dist: build>=0.10; extra == "dev"
Requires-Dist: twine>=4.0; extra == "dev"
